jarvisbot/__init__.py
jarvisbot/_base_client.py
jarvisbot/_client.py
jarvisbot/_compat.py
jarvisbot/_constants.py
jarvisbot/_exceptions.py
jarvisbot/_files.py
jarvisbot/_legacy_response.py
jarvisbot/_models.py
jarvisbot/_qs.py
jarvisbot/_resource.py
jarvisbot/_response.py
jarvisbot/_streaming.py
jarvisbot/_types.py
jarvisbot/_version.py
jarvisbot/pagination.py
jarvisbot/py.typed
jarvisbot/version.py
jarvisbot/_utils/__init__.py
jarvisbot/_utils/_logs.py
jarvisbot/_utils/_proxy.py
jarvisbot/_utils/_streams.py
jarvisbot/_utils/_sync.py
jarvisbot/_utils/_transform.py
jarvisbot/_utils/_typing.py
jarvisbot/_utils/_utils.py
jarvisbot/resources/__init__.py
jarvisbot/resources/completions.py
jarvisbot/resources/images.py
jarvisbot/resources/audio/__init__.py
jarvisbot/resources/audio/audio.py
jarvisbot/resources/audio/speech.py
jarvisbot/resources/audio/transcriptions.py
jarvisbot/resources/base/__init__.py
jarvisbot/resources/base/base.py
jarvisbot/resources/chat/__init__.py
jarvisbot/resources/chat/chat.py
jarvisbot/resources/chat/completions.py
jarvisbot/types/__init__.py
jarvisbot/types/completion.py
jarvisbot/types/completion_choice.py
jarvisbot/types/completion_create_params.py
jarvisbot/types/completion_usage.py
jarvisbot/types/image.py
jarvisbot/types/image_create_variation_params.py
jarvisbot/types/image_generate_params.py
jarvisbot/types/images_response.py
jarvisbot/types/audio/__init__.py
jarvisbot/types/audio/speech_create_params.py
jarvisbot/types/audio/transcription.py
jarvisbot/types/audio/transcription_create_params.py
jarvisbot/types/chat/__init__.py
jarvisbot/types/chat/chat_completion.py
jarvisbot/types/chat/chat_completion_assistant_message_param.py
jarvisbot/types/chat/chat_completion_chunk.py
jarvisbot/types/chat/chat_completion_content_part_image_param.py
jarvisbot/types/chat/chat_completion_content_part_param.py
jarvisbot/types/chat/chat_completion_content_part_text_param.py
jarvisbot/types/chat/chat_completion_function_call_option_param.py
jarvisbot_python-1.13.3.dist-info/METADATA
jarvisbot_python-1.13.3.dist-info/WHEEL
jarvisbot_python-1.13.3.dist-info/licenses/LICENSE
jarvisbot_python-1.13.3.dist-info/RECORD
